CONTRIBUTING.md
CONTRIBUTORS.txt
COPYING
COPYING.LESSER
MANIFEST.in
README.rst
VERSION.txt
pyproject.toml
requirements.txt
setup.py
docs/README.rst
docs/legal/CLA.txt
idf_converter/__init__.py
idf_converter/cli.py
idf_converter/py.typed
idf_converter/writer.py
idf_converter.egg-info/PKG-INFO
idf_converter.egg-info/SOURCES.txt
idf_converter.egg-info/dependency_links.txt
idf_converter.egg-info/entry_points.txt
idf_converter.egg-info/not-zip-safe
idf_converter.egg-info/requires.txt
idf_converter.egg-info/top_level.txt
idf_converter/lib/__init__.py
idf_converter/lib/anomaly.py
idf_converter/lib/atmos_correction.py
idf_converter/lib/constants.py
idf_converter/lib/data_type.py
idf_converter/lib/doppler.py
idf_converter/lib/downscale.py
idf_converter/lib/filter.py
idf_converter/lib/generic_grid.py
idf_converter/lib/geo.py
idf_converter/lib/granule.py
idf_converter/lib/interp.py
idf_converter/lib/mask.py
idf_converter/lib/n2_sst.py
idf_converter/lib/nir_bc.py
idf_converter/lib/rasterize.py
idf_converter/lib/sar.py
idf_converter/lib/scale.py
idf_converter/lib/swot.py
idf_converter/lib/time.py
idf_converter/lib/types.py
idf_converter/lib/vectors.py
idf_converter/lib/idf/v1/errors.py
idf_converter/lib/idf/v1/fmt.py
idf_converter/lib/idf/v1/grid_latlon.py
idf_converter/lib/idf/v1/grid_yx.py
idf_converter/lib/idf/v1/specs.py
idf_converter/lib/idf/v1/swath.py
idf_converter/lib/idf/v1/time_dependent.py
idf_converter/readers/bremen_amsr_l3_sic.py
idf_converter/readers/cmems_drifter.py
idf_converter/readers/cmorph.py
idf_converter/readers/ghrsst_l2p.py
idf_converter/readers/ibtracs_v4.py
idf_converter/readers/ifremer_scat_psi_backscatter.py
idf_converter/readers/iprc_argo_vi_monthly.py
idf_converter/readers/isas_monthly.py
idf_converter/readers/jamstec_argo_oi_monthly.py
idf_converter/readers/metoffice_en4_analysis.py
idf_converter/readers/metop_ascat_l2_wind.py
idf_converter/readers/mfwam.py
idf_converter/readers/netcdf_grid_latlon.py
idf_converter/readers/netcdf_grid_yx.py
idf_converter/readers/osisaf_l3_sic.py
idf_converter/readers/remss_l3_wind_bytemap.py
idf_converter/readers/remss_l3_wind_netcdf.py
idf_converter/readers/roemmich_gilson_monthly.py
idf_converter/readers/rtofs.py
idf_converter/readers/sentinel1_l1.py
