Metadata-Version: 2.2
Name: idf_converter
Version: 0.1.458
Summary: The idf_converter package provides tools to convert Earth Observation data into IDF files.
Home-page: https://seascope.oceandatalab.com
Author: Lucile Gaultier, Gilles Guitton, Sylvain Herlédan
Author-email: idf-support@oceandatalab.com
License: COPYING.LESSER
Classifier: Development Status :: 5 - Production/Stable
Classifier: Environment :: Console
Classifier: Intended Audience :: Science/Research
Classifier: License :: OSI Approved :: GNU Lesser General Public License v3 or later (LGPLv3+)
Classifier: Natural Language :: English
Classifier: Programming Language :: Python :: 3
Classifier: Programming Language :: Python :: 3.7
Classifier: Programming Language :: Python :: Implementation :: CPython
Classifier: Topic :: Scientific/Engineering :: GIS
Classifier: Typing :: Typed
Requires-Python: >=3.7
License-File: COPYING
License-File: COPYING.LESSER
Requires-Dist: importlib_resources; python_version < "3.9"
Requires-Dist: importlib_metadata; python_version < "3.10"
Requires-Dist: numpy<2.0,>=1.20
Requires-Dist: scipy
Requires-Dist: pyproj
Requires-Dist: netCDF4>=1.6.0
Requires-Dist: defusedxml
Requires-Dist: packaging
Requires-Dist: python-dateutil
Requires-Dist: tifffile
Requires-Dist: shapely
Requires-Dist: glymur
Requires-Dist: pyshp>=1.1.7
Requires-Dist: Pillow
Dynamic: author
Dynamic: author-email
Dynamic: classifier
Dynamic: description
Dynamic: description-content-type
Dynamic: home-page
Dynamic: license
Dynamic: requires-dist
Dynamic: requires-python
Dynamic: summary
